data_generator.py
db_connector.py
main.py
populator.py
schema_analyzer.py
utils.py
mysql_dummy_populator-1.0.0.dist-info/licenses/LICENSE
mysql_dummy_populator-1.0.0.dist-info/METADATA
mysql_dummy_populator-1.0.0.dist-info/WHEEL
mysql_dummy_populator-1.0.0.dist-info/entry_points.txt
mysql_dummy_populator-1.0.0.dist-info/top_level.txt
mysql_dummy_populator-1.0.0.dist-info/RECORD
