Metadata-Version: 2.4
Name: mysql-dummy-populator
Version: 1.0.0
Summary: A tool to populate MySQL databases with realistic dummy data
Home-page: https://github.com/vitebski/mysql-dummy-populator
Author: Slava Vitebski
Author-email: slava@redislabs.com
Project-URL: Bug Reports, https://github.com/vitebski/mysql-dummy-populator/issues
Project-URL: Source, https://github.com/vitebski/mysql-dummy-populator
Keywords: mysql,database,dummy data,testing,development
Classifier: Development Status :: 4 - Beta
Classifier: Intended Audience :: Developers
Classifier: Intended Audience :: Information Technology
Classifier: License :: OSI Approved :: MIT License
Classifier: Programming Language :: Python :: 3
Classifier: Programming Language :: Python :: 3.8
Classifier: Programming Language :: Python :: 3.9
Classifier: Programming Language :: Python :: 3.10
Classifier: Programming Language :: Python :: 3.11
Classifier: Topic :: Database
Classifier: Topic :: Software Development :: Testing
Classifier: Topic :: Utilities
Requires-Python: >=3.8
License-File: LICENSE
Requires-Dist: mysql-connector-python>=8.0.0
Requires-Dist: faker>=8.0.0
Requires-Dist: python-dotenv>=0.19.0
Requires-Dist: networkx>=2.6.0
Dynamic: author
Dynamic: author-email
Dynamic: classifier
Dynamic: description
Dynamic: description-content-type
Dynamic: home-page
Dynamic: keywords
Dynamic: license-file
Dynamic: project-url
Dynamic: requires-dist
Dynamic: requires-python
Dynamic: summary
